rabasar/__init__.py
rabasar/multilooking.py
rabasar/rabasar_algorithm.py
rabasar/rabasar_synthetic_example.py
rabasar/sar_image_stack_generation.py
rabasar/sar_image_stack_rendering.py
rabasar-0.0.1.dist-info/METADATA
rabasar-0.0.1.dist-info/WHEEL
rabasar-0.0.1.dist-info/top_level.txt
rabasar-0.0.1.dist-info/RECORD
