Metadata-Version: 2.1
Name: rabasar
Version: 0.0.1
Summary: Ratio-Based Multitemporal SAR Images Denoising - A (Pol/In)SAR image stack speckle reduction algorithm.
Home-page: https://www.charles-deledalle.fr/pages/rabasar
Author: Charles Deledalle, Sébastien Mounier, Cristiano Ulondu Mendes
Author-email: charles.deledalle@gmail.com
License: cecill
Project-URL: Source, https://bitbucket.org/charles_deledalle/rabasar2019-python/
Keywords: SAR,PolSAR,InSAR,speckle,filtering,images,wishart,temporal,stack
Platform: UNKNOWN
Requires-Python: >=3.10
Requires-Dist: attrs >=23.1.0
Requires-Dist: matplotlib >=3.7.2
Requires-Dist: mulog >=0.0.4
Requires-Dist: nptyping >=2.4.0
Requires-Dist: opencv-python
Requires-Dist: typing-extensions >=4.7.1
